setup.py
pikachu/__init__.py
pikachu.egg-info/PKG-INFO
pikachu.egg-info/SOURCES.txt
pikachu.egg-info/dependency_links.txt
pikachu.egg-info/not-zip-safe
pikachu.egg-info/top_level.txt