Metadata-Version: 1.1
Name: pikachu
Version: 0.1.2
Summary: Pika helpers
Home-page: https://github.com/DigitalDemiurge/pikachu
Author: Vitaliy Korobkin
Author-email: root@digitaldemiurge.me
License: MIT license
Platform: UNKNOWN
Classifier: Development Status :: 4 - Beta
Classifier: Environment :: Console
Classifier: License :: OSI Approved :: MIT License
Classifier: Programming Language :: Python
Classifier: Programming Language :: Python :: 2
Classifier: Programming Language :: Python :: 2.6
Classifier: Programming Language :: Python :: 2.7
Classifier: Topic :: Software Development :: Libraries :: Python Modules
Requires: pika (>= 0.9.13)
Requires: simplejson (>=2.6.1)
